django_estimators-0.2.1.dist-info/DESCRIPTION.rst
django_estimators-0.2.1.dist-info/METADATA
django_estimators-0.2.1.dist-info/RECORD
django_estimators-0.2.1.dist-info/WHEEL
django_estimators-0.2.1.dist-info/metadata.json
django_estimators-0.2.1.dist-info/top_level.txt
estimators/__init__.py
estimators/admin.py
estimators/apps.py
estimators/hashing.py
estimators/signals.py
estimators/storages.py
estimators/template_settings.py
estimators/utils.py
estimators/migrations/0001_initial.py
estimators/migrations/__init__.py
estimators/models/__init__.py
estimators/models/base.py
estimators/models/datasets.py
estimators/models/estimators.py
estimators/models/evaluations.py
