Metadata-Version: 2.0
Name: django-estimators
Version: 0.2.1
Summary: A django model to persist and track machine learning models
Home-page: https://github.com/fridiculous/django-estimators
Author: Simon Frid
Author-email: simon.frid@gmail.com
License: MIT License
Keywords: scikit-learn,sklearn,machine learning,artificial intelligence,ml,ai,estimators,version,versioning,benchmark,persist,storage,track,models,repository,evaluation,workflow
Platform: UNKNOWN
Classifier: Environment :: Web Environment
Classifier: Framework :: Django
Classifier: Framework :: Django :: 1.9
Classifier: Development Status :: 3 - Alpha
Classifier: Intended Audience :: Developers
Classifier: Intended Audience :: Science/Research
Classifier: License :: OSI Approved :: MIT License
Classifier: Operating System :: OS Independent
Classifier: Programming Language :: Python
Classifier: Programming Language :: Python :: 3
Classifier: Programming Language :: Python :: 3.4
Classifier: Programming Language :: Python :: 3.5
Classifier: Topic :: Internet :: WWW/HTTP
Classifier: Topic :: Internet :: WWW/HTTP :: Dynamic Content
Classifier: Topic :: Scientific/Engineering :: Artificial Intelligence
Classifier: Topic :: Software Development :: Libraries :: Python Modules
Classifier: Topic :: Software Development :: Version Control
Requires-Dist: dill (==0.2.5)
